CHANGELOG.txt
LICENSE.txt
MANIFEST.in
README.md
setup.py
test.py
keyauth/__init__.py
keyauth_tech.egg-info/PKG-INFO
keyauth_tech.egg-info/SOURCES.txt
keyauth_tech.egg-info/dependency_links.txt
keyauth_tech.egg-info/requires.txt
keyauth_tech.egg-info/top_level.txt