Metadata-Version: 2.1
Name: keyauth-tech
Version: 0.0.4
Summary: Authentication Tool for Authenticating Users, HWIDs and Licenses to keep your Code secure from malicious activities.
Home-page: https://keyauth.tech
Author: Collin Stokes
Author-email: rehan009a@outlook.com
License: MIT
Keywords: authentication,auth,keys,hwid
Classifier: Development Status :: 5 - Production/Stable
Classifier: License :: OSI Approved :: MIT License
Classifier: Programming Language :: Python
Classifier: Programming Language :: Python :: 3
Classifier: Programming Language :: Python :: 3.6
Classifier: Programming Language :: Python :: 3.7
Classifier: Programming Language :: Python :: 3.8
Classifier: Programming Language :: Python :: 3.9
Classifier: Programming Language :: Python :: 3.10
Classifier: Intended Audience :: Developers
Classifier: Topic :: Software Development :: Libraries :: Python Modules
Classifier: Operating System :: OS Independent
License-File: LICENSE.txt
